botdyn/__init__.py
botdyn/bd.config.json
botdyn/chat.py
botdyn/components.py
botdyn/core.py
botdyn/functional.py
botdyn/post_processors.py
botdyn/pre_processors.py
botdyn/prompts.py
botdyn/symbol.py
botdyn/utils.py
botdyn/backend/__init__.py
botdyn/backend/base.py
botdyn/backend/engine_clip.py
botdyn/backend/engine_crawler.py
botdyn/backend/engine_embedding.py
botdyn/backend/engine_file.py
botdyn/backend/engine_google.py
botdyn/backend/engine_gpt3.py
botdyn/backend/engine_imagerendering.py
botdyn/backend/engine_ocr.py
botdyn/backend/engine_output.py
botdyn/backend/engine_python.py
botdyn/backend/engine_speech.py
botdyn/backend/engine_userinput.py
botdyn/backend/settings.py
botdyn/backend/driver/chromedriver
botdyn/backend/driver/webclient.py
botdynamics-0.1.23.dist-info/LICENSE
botdynamics-0.1.23.dist-info/METADATA
botdynamics-0.1.23.dist-info/WHEEL
botdynamics-0.1.23.dist-info/top_level.txt
botdynamics-0.1.23.dist-info/RECORD
