Metadata-Version: 2.1
Name: botdynamics
Version: 0.1.23
Summary: A Neuro-Symbolic Framework for Python
Author-email: Marius-Constantin Dinu <office@alphacoreai.eu>
License: MIT License        
Project-URL: Homepage, https://alphacoreai.eu/
Project-URL: GitHub, https://github.com/Xpitfire/botdynamics
Keywords: symbolic programming,machine learning
Classifier: Programming Language :: Python :: 3
Classifier: License :: OSI Approved :: MIT License
Classifier: Operating System :: OS Independent
Requires-Python: >=3.7
License-File: LICENSE
Requires-Dist: natsort
Requires-Dist: numpy
Requires-Dist: tqdm
Requires-Dist: python-box
Requires-Dist: scikit-learn
Requires-Dist: torch
Requires-Dist: torchvision
Requires-Dist: pyyaml
Requires-Dist: transformers
Requires-Dist: openai
Requires-Dist: google-search-results
Requires-Dist: PyPDF2
Requires-Dist: ipython
Requires-Dist: beautifulsoup4
Requires-Dist: selenium
Requires-Dist: webdriver-manager
Requires-Dist: whisper
